consign/__init__.py
consign/decorator/__init__.py
consign/decorator/chainreactiondecorator.py
consign/decorator/consigndecorator.py
consign/decorator/consignorder.py
consign/decorator/consigntask.py
consign/decorator/repeatedcalldecorator.py
consign/utils/__init__.py
consign/utils/sleep.py
consign/workarea/__init__.py
consign/workarea/workarea.py
consign/worker/__init__.py
consign/worker/asyncworker.py
consign/worker/coroutineworker.py
consign/worker/iterationcontext.py
consign/worker/wait.py
pyconsign-1.0.3.dist-info/LICENSE
pyconsign-1.0.3.dist-info/METADATA
pyconsign-1.0.3.dist-info/WHEEL
pyconsign-1.0.3.dist-info/top_level.txt
pyconsign-1.0.3.dist-info/RECORD
