Metadata-Version: 2.1
Name: pyconsign
Version: 1.0.3
Summary: Generator-based Coroutines, Easy to use, Using the yield syntax
Home-page: https://github.com/SpectrePrediction/consign
Author: SpectrePrediction
Author-email: 1007108187@qq.com
License: MIT License
Keywords: coroutines,generator,yield
Classifier: License :: OSI Approved :: MIT License
Classifier: Programming Language :: Python :: 3
Classifier: Programming Language :: Python :: 3.5
Classifier: Programming Language :: Python :: 3.6
Classifier: Programming Language :: Python :: 3.7
Classifier: Programming Language :: Python :: 3.8
Classifier: Programming Language :: Python :: 3.9
Classifier: Programming Language :: Python :: 3.10
Classifier: Programming Language :: Python :: 3 :: Only
Requires-Python: >=3.5
License-File: LICENSE
Requires-Dist: contextvars ; python_version < "3.7"
